{
  "unversionedId": "zsh_plugin_standard",
  "id": "zsh_plugin_standard",
  "title": "Zsh Plugin Standard",
  "description": "What Is A Zsh Plugin?",
  "source": "@site/community/02_zsh_plugin_standard.md",
  "sourceDirName": ".",
  "slug": "/zsh_plugin_standard",
  "permalink": "/zh-Hans/community/zsh_plugin_standard",
  "editUrl": "https://digitalclouds.crowdin.com/z-shell/zh-Hans",
  "tags": [],
  "version": "current",
  "sidebarPosition": 2,
  "frontMatter": {
    "id": "zsh_plugin_standard",
    "title": "Zsh Plugin Standard",
    "sidebar_position": 2
  },
  "sidebar": "autoSideBar_2",
  "previous": {
    "title": "Zsh Knowledge Base",
    "permalink": "/zh-Hans/community/intro"
  },
  "next": {
    "title": "Zsh Native Scripting Handbook",
    "permalink": "/zh-Hans/community/zsh_handbook"
  }
}